custom_operators/__init__.py
custom_operators/operators/__init__.py
custom_operators/operators/true_division.py
custom_operators_ChrisPrein-1.0.0.dist-info/LICENSE
custom_operators_ChrisPrein-1.0.0.dist-info/METADATA
custom_operators_ChrisPrein-1.0.0.dist-info/WHEEL
custom_operators_ChrisPrein-1.0.0.dist-info/top_level.txt
custom_operators_ChrisPrein-1.0.0.dist-info/RECORD
